{
  "rows": [
    {
      "symbol": "MU",
      "name": "Micron Technology, Inc.",
      "price": 891.88,
      "changePercent": -4.702475718300227,
      "dollarVolume": 50638568537.03922,
      "marketCap": 1005803445405.88,
      "sector": "SEMICONDUCTORS & RELATED DEVICES",
      "theme": "記憶體",
      "isNew": false,
      "rankChange": 0,
      "streak": 64
    },
    {
      "symbol": "NVDA",
      "name": "Nvidia Corp",
      "price": 200.42,
      "changePercent": -3.7321677313992074,
      "dollarVolume": 32825839130.441715,
      "marketCap": 4850164000000,
      "sector": "SEMICONDUCTORS & RELATED DEVICES",
      "theme": "AI 晶片",
      "isNew": false,
      "rankChange": 0,
      "streak": 64
    },
    {
      "symbol": "TSLA",
      "name": "Tesla, Inc. Common Stock",
      "price": 381.59,
      "changePercent": -3.8040738126449614,
      "dollarVolume": 19182271670.828598,
      "marketCap": 1433146671934.89,
      "sector": "MOTOR VEHICLES & PASSENGER CAR BODIES",
      "theme": "電動車",
      "isNew": false,
      "rankChange": 2,
      "streak": 64
    },
    {
      "symbol": "SNDK",
      "name": "Sandisk Corporation Common Stock",
      "price": 1643.23,
      "changePercent": -0.20102760941124698,
      "dollarVolume": 17338491766.51657,
      "marketCap": 243345533038.34,
      "sector": "COMPUTER STORAGE DEVICES",
      "theme": "儲存裝置",
      "isNew": false,
      "rankChange": -1,
      "streak": 64
    },
    {
      "symbol": "AAPL",
      "name": "Apple Inc.",
      "price": 291.58,
      "changePercent": 0.3545000860437008,
      "dollarVolume": 15384591290.447315,
      "marketCap": 4282539262480,
      "sector": "ELECTRONIC COMPUTERS",
      "theme": "消費性電子",
      "isNew": false,
      "rankChange": 1,
      "streak": 64
    },
    {
      "symbol": "AVGO",
      "name": "Broadcom Inc. Common Stock",
      "price": 372.1,
      "changePercent": -5.1152590779273766,
      "dollarVolume": 14320611443.858385,
      "marketCap": 1761770031266.4001,
      "sector": "SEMICONDUCTORS & RELATED DEVICES",
      "theme": "網通晶片",
      "isNew": false,
      "rankChange": 3,
      "streak": 64
    },
    {
      "symbol": "MRVL",
      "name": "Marvell Technology, Inc. Common Stock",
      "price": 252.59,
      "changePercent": -5.354466426858511,
      "dollarVolume": 14046766593.558878,
      "marketCap": 220965732000,
      "sector": "SEMICONDUCTORS & RELATED DEVICES",
      "theme": "網通晶片",
      "isNew": false,
      "rankChange": -3,
      "streak": 54
    },
    {
      "symbol": "INTC",
      "name": "Intel Corp",
      "price": 107.04,
      "changePercent": -0.8154188287620416,
      "dollarVolume": 13167560590.312054,
      "marketCap": 537983040000.00006,
      "sector": "SEMICONDUCTORS & RELATED DEVICES",
      "theme": "CPU",
      "isNew": false,
      "rankChange": 0,
      "streak": 64
    },
    {
      "symbol": "MSFT",
      "name": "Microsoft Corp",
      "price": 397.36,
      "changePercent": -1.4997149302198782,
      "dollarVolume": 13034456110.954153,
      "marketCap": 2951762813981.44,
      "sector": "SERVICES-PREPACKAGED SOFTWARE",
      "theme": "雲端軟體 SaaS",
      "isNew": false,
      "rankChange": 1,
      "streak": 64
    },
    {
      "symbol": "AMD",
      "name": "Advanced Micro Devices",
      "price": 452.4,
      "changePercent": -4.859044594694066,
      "dollarVolume": 12749415119.880146,
      "marketCap": 737683729083.6,
      "sector": "SEMICONDUCTORS & RELATED DEVICES",
      "theme": "AI 晶片",
      "isNew": false,
      "rankChange": -3,
      "streak": 64
    },
    {
      "symbol": "GOOGL",
      "name": "Alphabet Inc. Class A Common Stock",
      "price": 356.38,
      "changePercent": -2.1632899577225047,
      "dollarVolume": 11636883687.48126,
      "marketCap": 2075557120000,
      "sector": "SERVICES-COMPUTER PROGRAMMING, DATA PROCESSING, ETC.",
      "theme": "雲端服務",
      "isNew": false,
      "rankChange": 1,
      "streak": 64
    },
    {
      "symbol": "META",
      "name": "Meta Platforms, Inc. Class A Common Stock",
      "price": 570.98,
      "changePercent": -2.3281274055320846,
      "dollarVolume": 9826194122.564394,
      "marketCap": 1253898109836.24,
      "sector": "SERVICES-COMPUTER PROGRAMMING, DATA PROCESSING, ETC.",
      "theme": "社群媒體",
      "isNew": false,
      "rankChange": 1,
      "streak": 64
    },
    {
      "symbol": "AMZN",
      "name": "Amazon.Com Inc",
      "price": 238,
      "changePercent": -2.5349113395306926,
      "dollarVolume": 9238170903.407524,
      "marketCap": 2560192045768,
      "sector": "RETAIL-CATALOG & MAIL-ORDER HOUSES",
      "theme": "電商與雲端",
      "isNew": false,
      "rankChange": -2,
      "streak": 64
    },
    {
      "symbol": "ORCL",
      "name": "Oracle Corp",
      "price": 201.26,
      "changePercent": -2.2107769301783256,
      "dollarVolume": 9235954457.505049,
      "marketCap": 578833017960,
      "sector": "SERVICES-PREPACKAGED SOFTWARE",
      "theme": "資料庫軟體",
      "isNew": false,
      "rankChange": 7,
      "streak": 64
    },
    {
      "symbol": "GOOG",
      "name": "Alphabet Inc. Class C Capital Stock",
      "price": 353.32,
      "changePercent": -2.475917082999814,
      "dollarVolume": 7096358888.385844,
      "marketCap": 1927713920000,
      "sector": "SERVICES-COMPUTER PROGRAMMING, DATA PROCESSING, ETC.",
      "theme": "雲端服務",
      "isNew": false,
      "rankChange": 0,
      "streak": 64
    },
    {
      "symbol": "SMCI",
      "name": "Super Micro Computer, Inc. Common Stock",
      "price": 29.27,
      "changePercent": -27.97736220472441,
      "dollarVolume": 6120662216.858184,
      "marketCap": 17603518968.14,
      "sector": "ELECTRONIC COMPUTERS",
      "theme": "AI 伺服器",
      "isNew": true,
      "rankChange": null,
      "streak": 1
    },
    {
      "symbol": "AMAT",
      "name": "Applied Materials Inc",
      "price": 497.01,
      "changePercent": -0.44069630015424144,
      "dollarVolume": 5769878809.1549635,
      "marketCap": 394605776304.3,
      "sector": "SEMICONDUCTORS & RELATED DEVICES",
      "theme": "半導體設備",
      "isNew": false,
      "rankChange": 2,
      "streak": 29
    },
    {
      "symbol": "TSM",
      "name": "Taiwan Semiconductor Manufacturing Company Ltd.",
      "price": 408.75,
      "changePercent": -4.479809310151434,
      "dollarVolume": 5441729078.7581625,
      "marketCap": 2119971247500,
      "sector": "—",
      "theme": "晶圓代工",
      "isNew": false,
      "rankChange": -4,
      "streak": 64
    },
    {
      "symbol": "LITE",
      "name": "Lumentum Holdings Inc. Common Stock",
      "price": 853.26,
      "changePercent": 3.833235981308411,
      "dollarVolume": 5006175180.533659,
      "marketCap": 66383628000,
      "sector": "COMMUNICATIONS EQUIPMENT, NEC",
      "theme": "光通訊元件",
      "isNew": false,
      "rankChange": -3,
      "streak": 64
    },
    {
      "symbol": "LRCX",
      "name": "Lam Research Corp",
      "price": 321.8,
      "changePercent": -1.6383420956107144,
      "dollarVolume": 4626020523.397672,
      "marketCap": 402433747800,
      "sector": "SPECIAL INDUSTRY MACHINERY, NEC",
      "theme": "半導體設備",
      "isNew": false,
      "rankChange": 4,
      "streak": 7
    },
    {
      "symbol": "GEV",
      "name": "GE Vernova Inc.",
      "price": 867.09,
      "changePercent": -5.766451122099652,
      "dollarVolume": 4620736416.09557,
      "marketCap": 233004420464.55002,
      "sector": "ELECTRONIC & OTHER ELECTRICAL EQUIPMENT (NO COMPUTER EQUIP)",
      "theme": "電力基礎建設",
      "isNew": false,
      "rankChange": 14,
      "streak": 2
    },
    {
      "symbol": "ASML",
      "name": "ASML Holding NV",
      "price": 1734.19,
      "changePercent": -2.451385724812542,
      "dollarVolume": 4550113892.2586975,
      "marketCap": 673121814774.06,
      "sector": "—",
      "theme": "半導體設備",
      "isNew": false,
      "rankChange": -2,
      "streak": 7
    },
    {
      "symbol": "PLTR",
      "name": "Palantir Technologies Inc. Class A Common Stock",
      "price": 130.21,
      "changePercent": -1.4083440599681876,
      "dollarVolume": 4012163024.022285,
      "marketCap": 298971448400.14,
      "sector": "SERVICES-PREPACKAGED SOFTWARE",
      "theme": "大數據分析",
      "isNew": false,
      "rankChange": -1,
      "streak": 64
    },
    {
      "symbol": "HOOD",
      "name": "Robinhood Markets, Inc. Class A Common Stock",
      "price": 86.36,
      "changePercent": 3.0917989733794955,
      "dollarVolume": 3715879349.1684628,
      "marketCap": 68326710519.28,
      "sector": "SECURITY BROKERS, DEALERS & FLOTATION COMPANIES",
      "theme": "線上券商",
      "isNew": true,
      "rankChange": null,
      "streak": 1
    },
    {
      "symbol": "BE",
      "name": "Bloom Energy Corporation",
      "price": 234.23,
      "changePercent": -9.776202765687,
      "dollarVolume": 3704437398.3149457,
      "marketCap": 66625287201.64,
      "sector": "ELECTRICAL INDUSTRIAL APPARATUS",
      "theme": "燃料電池",
      "isNew": false,
      "rankChange": 3,
      "streak": 4
    },
    {
      "symbol": "QCOM",
      "name": "Qualcomm Inc",
      "price": 191.2,
      "changePercent": -6.922402881900497,
      "dollarVolume": 3581470611.9681616,
      "marketCap": 201524800000,
      "sector": "RADIO & TV BROADCASTING & COMMUNICATIONS EQUIPMENT",
      "theme": "手機晶片",
      "isNew": false,
      "rankChange": -8,
      "streak": 33
    },
    {
      "symbol": "DELL",
      "name": "Dell Technologies Inc.",
      "price": 369.83,
      "changePercent": -3.1300749122531273,
      "dollarVolume": 3545467356.7864013,
      "marketCap": 120207393748.04,
      "sector": "ELECTRONIC COMPUTERS",
      "theme": "PC與伺服器",
      "isNew": false,
      "rankChange": 2,
      "streak": 13
    },
    {
      "symbol": "KLAC",
      "name": "KLA Corporation Common Stock",
      "price": 2135.64,
      "changePercent": -0.17435039287266896,
      "dollarVolume": 3488571611.5289426,
      "marketCap": 278973358948.44,
      "sector": "OPTICAL INSTRUMENTS & LENSES",
      "theme": "半導體檢測",
      "isNew": false,
      "rankChange": 8,
      "streak": 4
    },
    {
      "symbol": "CRDO",
      "name": "Credo Technology Group Holding Ltd Ordinary Shares",
      "price": 237.68,
      "changePercent": 1.4339364970979915,
      "dollarVolume": 3410482749.1276307,
      "marketCap": 43840061739.200005,
      "sector": "SEMICONDUCTORS & RELATED DEVICES",
      "theme": "高速傳輸晶片",
      "isNew": false,
      "rankChange": 3,
      "streak": 2
    },
    {
      "symbol": "NBIS",
      "name": "Nebius Group N.V. Class A Ordinary Shares",
      "price": 211.69,
      "changePercent": -3.829729238597132,
      "dollarVolume": 3352344630.476206,
      "marketCap": 46458564478.72,
      "sector": "—",
      "theme": "雲端服務",
      "isNew": false,
      "rankChange": -7,
      "streak": 22
    },
    {
      "symbol": "CAT",
      "name": "Caterpillar Inc.",
      "price": 856.16,
      "changePercent": -6.399912539630488,
      "dollarVolume": 3130198680.052389,
      "marketCap": 394340432165.27997,
      "sector": "CONSTRUCTION MACHINERY & EQUIP",
      "theme": "重型機械",
      "isNew": false,
      "rankChange": 15,
      "streak": 3
    },
    {
      "symbol": "LLY",
      "name": "Eli Lilly & Co.",
      "price": 1136.37,
      "changePercent": -0.7259670825034221,
      "dollarVolume": 3092028562.525725,
      "marketCap": 1070166681536.2198,
      "sector": "PHARMACEUTICAL PREPARATIONS",
      "theme": "減肥藥 GLP-1",
      "isNew": false,
      "rankChange": -6,
      "streak": 16
    },
    {
      "symbol": "AAOI",
      "name": "Applied Optoelectronics, Inc.",
      "price": 175.13,
      "changePercent": 7.520874263261297,
      "dollarVolume": 2983489591.763313,
      "marketCap": 14052915784.71,
      "sector": "SEMICONDUCTORS & RELATED DEVICES",
      "theme": "光通訊元件",
      "isNew": false,
      "rankChange": -8,
      "streak": 5
    },
    {
      "symbol": "NFLX",
      "name": "NetFlix Inc",
      "price": 82,
      "changePercent": 0.7247266920525776,
      "dollarVolume": 2977709033.9928374,
      "marketCap": 345285479296,
      "sector": "SERVICES-VIDEO TAPE RENTAL",
      "theme": "串流媒體",
      "isNew": false,
      "rankChange": 10,
      "streak": 8
    },
    {
      "symbol": "WDC",
      "name": "Western Digital Corp.",
      "price": 490.09,
      "changePercent": -5.336861624043895,
      "dollarVolume": 2956012738.094332,
      "marketCap": 168925265581.78998,
      "sector": "COMPUTER STORAGE DEVICES",
      "theme": "儲存裝置",
      "isNew": false,
      "rankChange": -4,
      "streak": 62
    },
    {
      "symbol": "STX",
      "name": "Seagate Technology Holdings PLC Ordinary Shares (Ireland)",
      "price": 815.99,
      "changePercent": -3.5484214134584677,
      "dollarVolume": 2837940425.0363927,
      "marketCap": 182968615182.08002,
      "sector": "COMPUTER STORAGE DEVICES",
      "theme": "儲存裝置",
      "isNew": false,
      "rankChange": 14,
      "streak": 4
    },
    {
      "symbol": "WMT",
      "name": "Walmart Inc. Common Stock",
      "price": 120.59,
      "changePercent": 1.4384253028263863,
      "dollarVolume": 2684086779.5168843,
      "marketCap": 959664765301.4501,
      "sector": "RETAIL-VARIETY STORES",
      "theme": "零售百貨",
      "isNew": false,
      "rankChange": 6,
      "streak": 18
    },
    {
      "symbol": "UNH",
      "name": "UNITEDHEALTH GROUP INCORPORATED (Delaware)",
      "price": 407.46,
      "changePercent": -1.3414043583535158,
      "dollarVolume": 2656149478.3330145,
      "marketCap": 370032518853.83997,
      "sector": "HOSPITAL & MEDICAL SERVICE PLANS",
      "theme": "醫療保險",
      "isNew": false,
      "rankChange": -4,
      "streak": 6
    },
    {
      "symbol": "ARM",
      "name": "Arm Holdings plc American Depositary Shares",
      "price": 307.43,
      "changePercent": -5.365388167210493,
      "dollarVolume": 2518859072.3570895,
      "marketCap": 328359453186.8,
      "sector": "—",
      "theme": "IP 設計",
      "isNew": false,
      "rankChange": -12,
      "streak": 16
    },
    {
      "symbol": "BRK.B",
      "name": "BERKSHIRE HATHAWAY Class B",
      "price": 483.68,
      "changePercent": -0.8385099534616673,
      "dollarVolume": 2461066065.3347383,
      "marketCap": 676333940891.36,
      "sector": "FIRE, MARINE & CASUALTY INSURANCE",
      "theme": "多元控股",
      "isNew": true,
      "rankChange": null,
      "streak": 1
    },
    {
      "symbol": "APP",
      "name": "Applovin Corporation Class A Common Stock",
      "price": 492.98,
      "changePercent": -5.349051532140391,
      "dollarVolume": 2431681750.7102704,
      "marketCap": 150719761360,
      "sector": "SERVICES-COMPUTER PROGRAMMING, DATA PROCESSING, ETC.",
      "theme": "行動廣告",
      "isNew": true,
      "rankChange": null,
      "streak": 1
    },
    {
      "symbol": "CSCO",
      "name": "Cisco Systems, Inc. Common Stock (DE)",
      "price": 118.8,
      "changePercent": -1.2961116650049869,
      "dollarVolume": 2354925201.5426984,
      "marketCap": 468242438202,
      "sector": "COMPUTER COMMUNICATIONS EQUIPMENT",
      "theme": "網路設備",
      "isNew": false,
      "rankChange": 3,
      "streak": 22
    },
    {
      "symbol": "JPM",
      "name": "JPMorgan Chase & Co.",
      "price": 309.14,
      "changePercent": -1.1384713783178773,
      "dollarVolume": 2314668301.8290434,
      "marketCap": 828344159760.52,
      "sector": "NATIONAL COMMERCIAL BANKS",
      "theme": "大型銀行",
      "isNew": false,
      "rankChange": -10,
      "streak": 5
    },
    {
      "symbol": "GS",
      "name": "Goldman Sachs Group Inc.",
      "price": 1001.29,
      "changePercent": -2.9767153419056043,
      "dollarVolume": 2307886807.8675137,
      "marketCap": 295387980573.08997,
      "sector": "SECURITY BROKERS, DEALERS & FLOTATION COMPANIES",
      "theme": "投資銀行",
      "isNew": false,
      "rankChange": -3,
      "streak": 3
    },
    {
      "symbol": "XOM",
      "name": "Exxon Mobil Corporation",
      "price": 150.62,
      "changePercent": 1.1483446377006299,
      "dollarVolume": 2204930489.0821905,
      "marketCap": 624311941540.4401,
      "sector": "PETROLEUM REFINING",
      "theme": "石油與天然氣",
      "isNew": false,
      "rankChange": 4,
      "streak": 2
    },
    {
      "symbol": "NOW",
      "name": "SERVICENOW, INC.",
      "price": 106.06,
      "changePercent": -0.8507058053659873,
      "dollarVolume": 2153647732.4638042,
      "marketCap": 109347860000,
      "sector": "SERVICES-PREPACKAGED SOFTWARE",
      "theme": "雲端軟體 SaaS",
      "isNew": false,
      "rankChange": -16,
      "streak": 19
    },
    {
      "symbol": "IREN",
      "name": "IREN Limited Ordinary Shares",
      "price": 51.52,
      "changePercent": -4.627915586819696,
      "dollarVolume": 2152471653.4533343,
      "marketCap": 18412149284.48,
      "sector": "FINANCE SERVICES",
      "theme": "比特幣/加密",
      "isNew": false,
      "rankChange": -8,
      "streak": 8
    },
    {
      "symbol": "TXN",
      "name": "Texas Instruments Incorporated",
      "price": 282.01,
      "changePercent": -2.293593874510621,
      "dollarVolume": 2082727113.9844809,
      "marketCap": 256655267989.91,
      "sector": "SEMICONDUCTORS & RELATED DEVICES",
      "theme": "類比IC",
      "isNew": true,
      "rankChange": null,
      "streak": 1
    },
    {
      "symbol": "COHR",
      "name": "Coherent Corp.",
      "price": 354.77,
      "changePercent": -0.3287070854638467,
      "dollarVolume": 2037421947.43461,
      "marketCap": 69406961911.17,
      "sector": "OPTICAL INSTRUMENTS & LENSES",
      "theme": "光學元件",
      "isNew": false,
      "rankChange": -9,
      "streak": 3
    },
    {
      "symbol": "BAC",
      "name": "Bank of America Corporation",
      "price": 54.54,
      "changePercent": 0.22050716648290597,
      "dollarVolume": 2027047871.6104872,
      "marketCap": 387048054105.54,
      "sector": "NATIONAL COMMERCIAL BANKS",
      "theme": "大型銀行",
      "isNew": true,
      "rankChange": null,
      "streak": 1
    }
  ],
  "asOf": "2026-06-10T20:00:00.000Z",
  "generatedAt": "2026-06-11T07:25:09.968Z",
  "source": "polygon",
  "aiSource": "gemini",
  "themeSummary": [
    {
      "theme": "光通訊元件",
      "reason": "隨著AI與數據中心需求增長，高速傳輸與光通訊技術被視為關鍵基礎設施，帶動相關元件需求。",
      "symbols": [
        "LITE",
        "AAOI"
      ],
      "count": 2,
      "avgChange": 5.677055122284854
    },
    {
      "theme": "線上券商",
      "reason": "市場波動與散戶交易活動增加，可能為提供低成本交易服務的線上券商帶來利多。",
      "symbols": [
        "HOOD"
      ],
      "count": 1,
      "avgChange": 3.0917989733794955
    },
    {
      "theme": "零售百貨",
      "reason": "消費者支出數據表現穩健，大型零售商因其防禦性特質和股息吸引力而受到關注。",
      "symbols": [
        "WMT"
      ],
      "count": 1,
      "avgChange": 1.4384253028263863
    },
    {
      "theme": "串流媒體",
      "reason": "儘管競爭激烈，但訂閱用戶增長和內容策略調整，持續吸引投資者目光。",
      "symbols": [
        "NFLX"
      ],
      "count": 1,
      "avgChange": 0.7247266920525776
    },
    {
      "theme": "石油與天然氣",
      "reason": "國際油價波動或地緣政治事件，可能推升能源股表現。",
      "symbols": [
        "XOM"
      ],
      "count": 1,
      "avgChange": 1.1483446377006299
    },
    {
      "theme": "大型銀行",
      "reason": "在利率環境變化和經濟前景不明朗下，大型銀行因其穩健的資產負債表和多元業務而受到青睞。",
      "symbols": [
        "BAC"
      ],
      "count": 1,
      "avgChange": 0.22050716648290597
    }
  ],
  "newEntrants": [
    {
      "symbol": "SMCI",
      "name": "Super Micro Computer, Inc. Common Stock",
      "theme": "AI 伺服器",
      "changePercent": -27.97736220472441,
      "reason": "宣布籌資70億美元，引發股權稀釋疑慮導致股價重挫。"
    },
    {
      "symbol": "HOOD",
      "name": "Robinhood Markets, Inc. Class A Common Stock",
      "theme": "線上券商",
      "changePercent": 3.0917989733794955,
      "reason": "受惠比特幣反彈及獲准跨足IPO承銷業務，股價上漲。"
    },
    {
      "symbol": "BRK.B",
      "name": "BERKSHIRE HATHAWAY Class B",
      "theme": "多元控股",
      "changePercent": -0.8385099534616673,
      "reason": "近期無明確個股消息，可能受族群輪動帶動。"
    },
    {
      "symbol": "APP",
      "name": "Applovin Corporation Class A Common Stock",
      "theme": "行動廣告",
      "changePercent": -5.349051532140391,
      "reason": "近期無明確個股消息，可能受族群輪動帶動。"
    },
    {
      "symbol": "TXN",
      "name": "Texas Instruments Incorporated",
      "theme": "類比IC",
      "changePercent": -2.293593874510621,
      "reason": "晶片股近期自高檔拉回，獲利了結賣壓出籠。"
    },
    {
      "symbol": "BAC",
      "name": "Bank of America Corporation",
      "theme": "大型銀行",
      "changePercent": 0.22050716648290597,
      "reason": "美國司法部調查銀行關閉帳戶問題，引發市場關注。"
    }
  ],
  "marketBriefing": {
    "highlights": "本日成交重點聚焦於科技股，特別是AI相關領域，但市場情緒呈現複雜。記憶體類股如美光（MU）因AI資料中心對高頻寬記憶體（HBM）的強勁需求而受到資金追捧，儘管美國汽車、醫療設備等產業團體警告記憶體短缺可能衝擊供應鏈並推升物價，顯示AI需求已對其他產業造成排擠效應。AI晶片股如Nvidia（NVDA）和AMD（AMD）雖然成交量大，但股價普遍下跌，部分原因可能來自市場對AI成本飆升和估值過高的擔憂，以及博通（AVGO）財測不如預期引發的賣壓。然而，也有部分投資人將此視為逢低買進的機會。此外，Intel（INTC）受惠於Google的AI晶片代工大單傳聞而有亮眼表現，顯示市場對其晶圓代工業務的期待。",
    "eventsPast": [
      {
        "title": "美國多產業團體警告AI記憶體短缺",
        "detail": "美國汽車、醫療設備、零售等九大產業協會聯名致函政府，警告AI資料中心對記憶體晶片的需求激增，導致記憶體價格飆升，並排擠其他產業的供應，可能引發通膨並衝擊關鍵供應鏈。"
      },
      {
        "title": "博通財測不如預期引發AI晶片股賣壓",
        "detail": "博通（AVGO）公布的AI晶片銷售展望低於市場預期，導致其股價重挫，並引發了整體AI晶片股的賣壓，費城半導體指數盤中一度大跌。"
      },
      {
        "title": "Google傳下英特爾AI晶片大單",
        "detail": "有報導指出，Google母公司Alphabet（GOOGL）已委託英特爾（INTC）於2028年生產超過300萬顆自研AI晶片，激勵英特爾股價應聲飆漲。"
      },
      {
        "title": "Marvell財報與財測優於預期",
        "detail": "Marvell Technology（MRVL）公布的上季財報和本季財測雙雙優於預期，並上調全年財測，主因AI資料中心基礎建設對網路和客製化晶片的需求「異常強勁」。"
      },
      {
        "title": "COMPUTEX聚焦AI與機器人",
        "detail": "COMPUTEX 2026以「AI Together」為主題，並將機器人與智慧移動納入三大趨勢，顯示AI題材正從聊天轉向真實世界的應用，Nvidia也發表了人形機器人參考設計。"
      }
    ],
    "eventsUpcoming": []
  }
}